recipe_scrapers/__init__.py
recipe_scrapers/__version__.py
recipe_scrapers/_abstract.py
recipe_scrapers/_exceptions.py
recipe_scrapers/_factory.py
recipe_scrapers/_schemaorg.py
recipe_scrapers/_utils.py
recipe_scrapers/abril.py
recipe_scrapers/acouplecooks.py
recipe_scrapers/afghankitchenrecipes.py
recipe_scrapers/akispetretzikis.py
recipe_scrapers/albertheijn.py
recipe_scrapers/allrecipes.py
recipe_scrapers/alltomat.py
recipe_scrapers/altonbrown.py
recipe_scrapers/amazingribs.py
recipe_scrapers/ambitiouskitchen.py
recipe_scrapers/archanaskitchen.py
recipe_scrapers/arla.py
recipe_scrapers/atelierdeschefs.py
recipe_scrapers/averiecooks.py
recipe_scrapers/bakingmischeif.py
recipe_scrapers/bakingsense.py
recipe_scrapers/bbcfood.py
recipe_scrapers/bbcgoodfood.py
recipe_scrapers/bettybossi.py
recipe_scrapers/bettycrocker.py
recipe_scrapers/bigoven.py
recipe_scrapers/blueapron.py
recipe_scrapers/bodybuilding.py
recipe_scrapers/bonappetit.py
recipe_scrapers/bowlofdelicious.py
recipe_scrapers/budgetbytes.py
recipe_scrapers/castironketo.py
recipe_scrapers/cdkitchen.py
recipe_scrapers/chefkoch.py
recipe_scrapers/closetcooking.py
recipe_scrapers/comidinhasdochef.py
recipe_scrapers/cookeatshare.py
recipe_scrapers/cookieandkate.py
recipe_scrapers/cookingcircle.py
recipe_scrapers/cookinglight.py
recipe_scrapers/cookpad.py
recipe_scrapers/cookstr.py
recipe_scrapers/coop.py
recipe_scrapers/copykat.py
recipe_scrapers/countryliving.py
recipe_scrapers/cucchiaio.py
recipe_scrapers/cuisineaz.py
recipe_scrapers/cybercook.py
recipe_scrapers/davidlebovitz.py
recipe_scrapers/delish.py
recipe_scrapers/ditchthecarbs.py
recipe_scrapers/domesticateme.py
recipe_scrapers/downshiftology.py
recipe_scrapers/dr.py
recipe_scrapers/eatingbirdfood.py
recipe_scrapers/eatingwell.py
recipe_scrapers/eatsmarter.py
recipe_scrapers/eatwhattonight.py
recipe_scrapers/emmikochteinfach.py
recipe_scrapers/epicurious.py
recipe_scrapers/ethanchlebowski.py
recipe_scrapers/farmhousedelivery.py
recipe_scrapers_ap_fork-14.24.7.dist-info/LICENSE
recipe_scrapers_ap_fork-14.24.7.dist-info/METADATA
recipe_scrapers_ap_fork-14.24.7.dist-info/WHEEL
recipe_scrapers_ap_fork-14.24.7.dist-info/top_level.txt
recipe_scrapers_ap_fork-14.24.7.dist-info/RECORD
