Metadata-Version: 2.1
Name: recipe-scrapers-ap-fork
Version: 14.24.7
Summary: Python package, scraping recipes from all over the internet
Author-email: Hristo Harsev <r+pypi@hharsev.com>
License: MIT License
Project-URL: Homepage, https://github.com/hhursev/recipe-scrapers/
Keywords: python,recipes,scraper,harvest,recipe-scraper,recipe-scrapers
Classifier: Programming Language :: Python :: 3
Classifier: License :: OSI Approved :: MIT License
Classifier: Intended Audience :: Developers
Classifier: Operating System :: OS Independent
Classifier: Topic :: Internet :: WWW/HTTP
Requires-Python: >=3.6
License-File: LICENSE
Requires-Dist: beautifulsoup4 (>=4.10.0)
Requires-Dist: extruct (>=0.8.0)
Requires-Dist: isodate (>=0.6.1)
Requires-Dist: requests (>=2.19.1)
